<xml>
    <oobbPart>
        <oobbID>MP-DCSO-03-02</oobbID>
        <typeOOBB>MP</typeOOBB>
        <typeName>Mounting Plate</typeName>
        <widthOOBB>3</widthOOBB>
        <heightOOBB>2</heightOOBB>
        <name>Mounting Plate (DC Soxcket 2.1 mm 3x2)</name>
        <hexID></hexID>
        <widthMM>53</widthMM>
        <heightMM>33</heightMM>
		<oobbSort>10</oobbSort>
		<numPieces>1</numPieces>
        <note></note>
        <description>Mounting plate for 2.1 mm DC socket with screw terminals, 3 units wide and 2 units tall.</description>
    </oobbPart>
</xml>
